pysnn/__init__.py
pysnn/connection.py
pysnn/datasets.py
pysnn/encoding.py
pysnn/file_io.py
pysnn/functional.py
pysnn/learning.py
pysnn/network.py
pysnn/neuron.py
pysnn/utils.py
pysnn-0.1.1.dist-info/METADATA
pysnn-0.1.1.dist-info/RECORD
pysnn-0.1.1.dist-info/WHEEL
pysnn-0.1.1.dist-info/top_level.txt
