Metadata-Version: 2.1
Name: pysnn
Version: 0.1.1
Summary: Framework for engineering and simulating spiking neural networks, built on top of PyTorch.
Home-page: UNKNOWN
Author: Bas Buller
Author-email: bas.buller@gmail.com
License: UNKNOWN
Platform: UNKNOWN
Requires-Python: >=3.6.0
Provides-Extra: tests
Provides-Extra: examples
Requires-Dist: torch (>=1.2.0)
Requires-Dist: torchvision
Requires-Dist: matplotlib
Requires-Dist: numpy
Requires-Dist: pandas
Requires-Dist: sklearn
Requires-Dist: pre-commit
Provides-Extra: examples
Requires-Dist: gym; extra == 'examples'
Requires-Dist: tensorflow (>=2.0.0); extra == 'examples'
Requires-Dist: ray[tune]; extra == 'examples'
Requires-Dist: ray[debug]; extra == 'examples'
Requires-Dist: requests; extra == 'examples'
Requires-Dist: bayesian-optimization; extra == 'examples'
Provides-Extra: tests
Requires-Dist: pytest; extra == 'tests'
Requires-Dist: coverage; extra == 'tests'
Requires-Dist: pytest-cov; extra == 'tests'
